[
{"device_number": 0, "device_name": "NVIDIA GeForce RTX 5070", "architecture": "sm_120", "multi_processor_count": 48, "clock_rate": 2.512},
{"name": "mma_tf32_16_16_8", "runtime": 925.651, "tops": 14.2539, "frequency": 2317},
{"name": "mma_f16_16_16_16", "runtime": 462.919, "tops": 57.0041, "frequency": 2317},
{"name": "mma_bf16_16_16_16", "runtime": 462.911, "tops": 57.0051, "frequency": 2317},
{"name": "mma_s8_16_16_16", "runtime": 231.459, "tops": 114.009, "frequency": 2317},
{"name": "mma_s8_16_8_32", "runtime": 115.944, "tops": 227.595, "frequency": 2317},
{"name": "mma_e4m3_16_8_32", "runtime": 231.576, "tops": 113.951, "frequency": 2317},
{"name": "mma_e5m2_16_8_32", "runtime": 231.569, "tops": 113.954, "frequency": 2317},
{"name": "mma_s4_8_8_32", "runtime": 450.327, "tops": 29.299, "frequency": 2317},
{"name": "mma_e2m1_16_8_64", "runtime": 116.716, "tops": 452.178, "frequency": 2317},
{"name": "mma_e3m2_16_8_32", "runtime": 231.578, "tops": 113.95, "frequency": 2317},
{"name": "bmma_b1_8_8_128_xor", "runtime": 1197.93, "tops": 44.0564, "frequency": 2317},
{"name": "bmma_b1_8_8_128_and", "runtime": 532.569, "tops": 99.0981, "frequency": 2317},
{"name": "bmma_b1_16_8_256_xor", "runtime": 2779.34, "tops": 75.9556, "frequency": 2317},
{"name": "bmma_b1_16_8_256_and", "runtime": 985.5, "tops": 214.212, "frequency": 2317},
{"name": "mma_tf32_16_16_8", "runtime": 925.62, "tops": 14.2544, "frequency": 2317},
{"name": "mma_f16_16_16_16", "runtime": 462.911, "tops": 57.0051, "frequency": 2317},
{"name": "mma_bf16_16_16_16", "runtime": 462.899, "tops": 57.0065, "frequency": 2317},
{"name": "mma_s8_16_16_16", "runtime": 231.449, "tops": 114.013, "frequency": 2317},
{"name": "mma_s8_16_8_32", "runtime": 115.942, "tops": 227.599, "frequency": 2317},
{"name": "mma_e4m3_16_8_32", "runtime": 231.578, "tops": 113.95, "frequency": 2317},
{"name": "mma_e5m2_16_8_32", "runtime": 231.592, "tops": 113.943, "frequency": 2317},
{"name": "mma_s4_8_8_32", "runtime": 450.303, "tops": 29.3006, "frequency": 2317},
{"name": "mma_e2m1_16_8_64", "runtime": 116.709, "tops": 452.205, "frequency": 2317},
{"name": "mma_e3m2_16_8_32", "runtime": 231.591, "tops": 113.944, "frequency": 2317},
{"name": "bmma_b1_8_8_128_xor", "runtime": 1200.3, "tops": 43.9695, "frequency": 2317},
{"name": "bmma_b1_8_8_128_and", "runtime": 532.556, "tops": 99.1006, "frequency": 2317},
{"name": "bmma_b1_16_8_256_xor", "runtime": 2779.56, "tops": 75.9495, "frequency": 2317},
{"name": "bmma_b1_16_8_256_and", "runtime": 985.49, "tops": 214.214, "frequency": 2317},
{"name": "mma_tf32_16_16_8", "runtime": 925.626, "tops": 14.2543, "frequency": 2317},
{"name": "mma_f16_16_16_16", "runtime": 462.923, "tops": 57.0035, "frequency": 2317},
{"name": "mma_bf16_16_16_16", "runtime": 462.896, "tops": 57.0069, "frequency": 2317},
{"name": "mma_s8_16_16_16", "runtime": 231.451, "tops": 114.012, "frequency": 2317},
{"name": "mma_s8_16_8_32", "runtime": 115.936, "tops": 227.61, "frequency": 2317},
{"name": "mma_e4m3_16_8_32", "runtime": 231.568, "tops": 113.955, "frequency": 2317},
{"name": "mma_e5m2_16_8_32", "runtime": 231.569, "tops": 113.954, "frequency": 2317},
{"name": "mma_s4_8_8_32", "runtime": 450.282, "tops": 29.3019, "frequency": 2317},
{"name": "mma_e2m1_16_8_64", "runtime": 116.706, "tops": 452.22, "frequency": 2317},
{"name": "mma_e3m2_16_8_32", "runtime": 231.565, "tops": 113.956, "frequency": 2317},
{"name": "bmma_b1_8_8_128_xor", "runtime": 1200.26, "tops": 43.9708, "frequency": 2317},
{"name": "bmma_b1_8_8_128_and", "runtime": 532.527, "tops": 99.1059, "frequency": 2317},
{"name": "bmma_b1_16_8_256_xor", "runtime": 2779.56, "tops": 75.9496, "frequency": 2317},
{"name": "bmma_b1_16_8_256_and", "runtime": 985.525, "tops": 214.207, "frequency": 2317}
]
